markdown_query-0.5.12.dist-info/METADATA
markdown_query-0.5.12.dist-info/WHEEL
mq/__init__.py
mq/mq.abi3.so
mq/mq.pyi
mq/py.typed
markdown_query-0.5.12.dist-info/RECORD
