Metadata-Version: 2.4
Name: markdown-query
Version: 0.5.12
Classifier: Programming Language :: Rust
Classifier: Programming Language :: Python
Summary: Python bindings for mq, a jq-like command-line tool for Markdown processing
Keywords: markdown,jq,command-line,tool
Home-Page: https://mqlang.org/
Author: Takahiro Sato <harehare1110@gmail.com>
Author-email: harehare <harehare1110@gmail.com>
License: MIT
Requires-Python: >=3.10
Project-URL: Documentation, https://mqlang.org/book/
Project-URL: Homepage, https://mqlang.org/
Project-URL: Issues, https://github.com/harehare/mq/issues
Project-URL: Repository, https://github.com/harehare/mq.git
